ssind/__init__.py
ssind/app.py
ssind/lighthouse.py
ssind/ssind.py
ssind/ssind_0.bak
ssind/ssind_2.bak
ssind/mockups/devices.json
ssind/mockups/mockup.png
ssind/templates/index.html
ssind-0.1.3.dist-info/LICENSE
ssind-0.1.3.dist-info/METADATA
ssind-0.1.3.dist-info/WHEEL
ssind-0.1.3.dist-info/entry_points.txt
ssind-0.1.3.dist-info/top_level.txt
ssind-0.1.3.dist-info/RECORD
