Metadata-Version: 2.1
Name: ssind
Version: 0.1.3
Summary: Take Unlimited ScreenShot Automation and make a report
Home-page: https://github.com/irfnrdh/ssind/issues
Author: Irfannur Diah
Author-email: irfnrdh@gmail.com
License: AGPLv3
Project-URL: Documentation, https://github.com/irfnrdh/ssind/wiki
Project-URL: Source Code, https://github.com/irfnrdh/ssind
Project-URL: Issue Tracker, https://github.com/irfnrdh/ssind/issues
Keywords: sample setuptools development
Classifier: Development Status :: 3 - Alpha
Classifier: Intended Audience :: Developers
Classifier: Topic :: Software Development :: Build Tools
Classifier: License :: OSI Approved :: MIT License
Classifier: Programming Language :: Python :: 3.9
License-File: LICENSE
Requires-Dist: Flask
Requires-Dist: pdfkit
Requires-Dist: tqdm
Requires-Dist: click
Requires-Dist: selenium
Requires-Dist: requests
